prompt_searcher/__init__.py
prompt_searcher/core/__init__.py
prompt_searcher/core/agents/__init__.py
prompt_searcher/core/agents/anthropic_agent.py
prompt_searcher/core/agents/custom_agent.py
prompt_searcher/core/agents/groq_agent.py
prompt_searcher/core/agents/openai_agent.py
prompt_searcher/core/interfaces/__init__.py
prompt_searcher/core/interfaces/agent.py
prompt_searcher/core/interfaces/loss.py
prompt_searcher-0.1.1.dist-info/METADATA
prompt_searcher-0.1.1.dist-info/WHEEL
prompt_searcher-0.1.1.dist-info/top_level.txt
prompt_searcher-0.1.1.dist-info/RECORD
