Metadata-Version: 2.1
Name: prompt_searcher
Version: 0.1.1
Summary: PromptSearcher is an automatic tool designed to find the best prompt in both supervised and unsupervised scenarios. This project draws inspiration from traditional neural network learning techniques.
Home-page: https://github.com/octaviusp/PromptSearcher
Author: octaviopavon
Author-email: octavio.pavon@botman-ai.com
License: MIT
Classifier: Programming Language :: Python :: 3.12
Classifier: License :: OSI Approved :: MIT License
Classifier: Operating System :: OS Independent
Requires-Python: >=3.12
Requires-Dist: openai <2.0.0,>=1.51.2
Requires-Dist: polars <2.0.0,>=1.9.0
Requires-Dist: numpy <3.0.0,>=2.1.2
Requires-Dist: python-dotenv <2.0.0,>=1.0.1
Requires-Dist: anthropic <1.0.0,>=0.36.1
Requires-Dist: groq <1.0.0,>=0.11.0
Requires-Dist: matplotlib <4.0.0,>=3.9.2
Provides-Extra: dev
Requires-Dist: pytest <8.0.0,>=7.4.3 ; extra == 'dev'
Requires-Dist: python-dotenv <2.0.0,>=1.0.0 ; extra == 'dev'
